LICENSE
MANIFEST
MANIFEST.in
Makefile
README.rst
conftest.py
pytest.ini
requirements-dev.txt
requirements-test.txt
requirements.txt
setup.cfg
setup.py
tox.ini
eddie/__init__.py
eddie/bot.py
eddie.egg-info/PKG-INFO
eddie.egg-info/SOURCES.txt
eddie.egg-info/dependency_links.txt
eddie.egg-info/requires.txt
eddie.egg-info/top_level.txt
eddie/endpoints/__init__.py
eddie/endpoints/http.py
eddie/endpoints/telegram.py
eddie/endpoints/twitter.py
eddie/endpoints/http/index.html
tests/__init__.py
tests/base.py
tests/conftest.py
tests/http_test.py
tests/test_telegram.py
tests/test_twitter.py