Metadata-Version: 1.1
Name: eddie
Version: 0.9.4
Summary: A lib to create chatbots
Home-page: http://github.com/greenkey/eddie/
Author: Lorenzo Mele
Author-email: greenkey@loman.it
License: UNKNOWN
Keywords: chat,chatbot,telegram,twitter
Platform: any
Classifier: Development Status :: 4 - Beta
Classifier: Programming Language :: Python :: 2
Classifier: Programming Language :: Python :: 2.7
Classifier: Programming Language :: Python :: 3
Classifier: Programming Language :: Python :: 3.3
Classifier: Programming Language :: Python :: 3.4
Classifier: Programming Language :: Python :: 3.5
Classifier: Programming Language :: Python :: 3.6
Classifier: Natural Language :: English
Classifier: Intended Audience :: Developers
Classifier: License :: OSI Approved :: GNU General Public License v3 (GPLv3)
Classifier: Operating System :: OS Independent
Classifier: Topic :: Software Development :: Libraries :: Python Modules
